LICENSE
setup.cfg
setup.py
UniMathLib.egg-info/PKG-INFO
UniMathLib.egg-info/SOURCES.txt
UniMathLib.egg-info/dependency_links.txt
UniMathLib.egg-info/not-zip-safe
UniMathLib.egg-info/top_level.txt
unimathlib/__init__.py
unimathlib/Linear/__init__.py
unimathlib/Linear/linreg.py
unimathlib/MathFunc/__init__.py
unimathlib/MathFunc/matrix.py
unimathlib/MathFunc/vector.py
unimathlib/fin/__init__.py
unimathlib/fin/finance.py
unimathlib/timeSeriesAnalys/__init__.py
unimathlib/timeSeriesAnalys/tsy.py