Metadata-Version: 2.1
Name: UniMathLib
Version: 0.0.8.1
Summary: UniMathLib is a Python library that provides essential tools for        working with mathematical vectors and matrices. It simplifies tasks like vector        and matrix operations, linear system solving, determinant calculation, and more.        UniMathLib offers an intuitive interface for performing mathematical operations        efficiently.
Home-page: https://github.com/VIA-s-acc/UnivMathLib2
Author: Via
Author-email: hroyango@my.msu.ru
License: GNU GPLv3
Platform: UNKNOWN
License-File: LICENSE
